whatllm/__init__.py
whatllm/__main__.py
whatllm/cli.py
whatllm/llm_list.py
whatllm/ram.py
whatllm/vram.py
whatllm-0.1.1.dist-info/METADATA
whatllm-0.1.1.dist-info/WHEEL
whatllm-0.1.1.dist-info/entry_points.txt
whatllm-0.1.1.dist-info/top_level.txt
whatllm-0.1.1.dist-info/RECORD
